re_wx-0.1.0.data/data/rewx/icon.png
rewx/__init__.py
rewx/bitmap_support.py
rewx/components.py
rewx/core.py
rewx/deleteme.py
rewx/dispatch.py
rewx/icon.png
rewx/util.py
rewx/widgets.py
rewx/examples/__init__.py
rewx/examples/issue0002.py
rewx/examples/issue0003.py
rewx/examples/issue0003b.py
rewx/examples/issue0003c.py
rewx/examples/issue0003d.py
rewx/examples/issue0004.py
tests/__init__.py
tests/test_create_element.py
tests/test_nested_components.py
tests/test_widgets.py
tests/images/__init__.py
tests/test_components/__init__.py
tests/test_components/test_gauge.py
tests/test_components/test_staticbitmap.py
tests/test_components/test_textctrl.py
re_wx-0.1.0.dist-info/LICENSE
re_wx-0.1.0.dist-info/METADATA
re_wx-0.1.0.dist-info/WHEEL
re_wx-0.1.0.dist-info/top_level.txt
re_wx-0.1.0.dist-info/RECORD
