Metadata-Version: 2.1
Name: re-wx
Version: 0.1.0
Summary: A library for building modern declarative desktop applications in WX
Home-page: https://github.com/chriskiehl/re-wx
Author: Chris Kiehl
Author-email: me@chriskiehl.com
License: UNKNOWN
Platform: UNKNOWN
Classifier: Development Status :: 2 - Pre-Alpha
Classifier: Programming Language :: Python :: 3
Classifier: License :: OSI Approved :: MIT License
Classifier: Operating System :: Microsoft :: Windows
Classifier: Operating System :: MacOS
Classifier: Operating System :: POSIX :: Linux
Classifier: Intended Audience :: End Users/Desktop
Classifier: Topic :: Software Development :: User Interfaces
Requires-Python: >=3.6
Requires-Dist: wxpython (>=4.1.0)
